src/__init__.py
src/main.py
macabake-0.0.3.dist-info/entry_points.txt
macabake-0.0.3.dist-info/WHEEL
macabake-0.0.3.dist-info/METADATA
macabake-0.0.3.dist-info/RECORD
