Metadata-Version: 2.1
Name: macabake
Version: 0.0.3
Summary: 
Author: Sam Korn
Author-email: korn94sam@gmail.com
Requires-Python: >=3.8,<4.0
Classifier: Programming Language :: Python :: 3
Classifier: Programming Language :: Python :: 3.10
Classifier: Programming Language :: Python :: 3.8
Classifier: Programming Language :: Python :: 3.9
Requires-Dist: click (>=8.1.3,<9.0.0)
Requires-Dist: lnd-grpc-client (>=0.4.4,<0.5.0)
